legend_dashboard-1.0.0.dist-info/licenses/LICENSE
legenddashboard/__init__.py
legenddashboard/base.py
legenddashboard/dashboard.py
legenddashboard/util.py
legenddashboard/geds/ged_monitoring.py
legenddashboard/geds/string_visulization.py
legenddashboard/geds/cal/__init__.py
legenddashboard/geds/cal/cal_monitoring.py
legenddashboard/geds/cal/detailed_plots.py
legenddashboard/geds/cal/summary_plots.py
legenddashboard/geds/cal/tracking_plots.py
legenddashboard/geds/phy/__init__.py
legenddashboard/geds/phy/phy_monitoring.py
legenddashboard/geds/phy/phy_plots.py
legenddashboard/llama/llama_monitoring.py
legenddashboard/muon/__init__.py
legenddashboard/muon/muon_monitoring.py
legenddashboard/muon/muon_plots.py
legenddashboard/spms/sipm_monitoring.py
legenddashboard/spms/sipm_plots.py
legend_dashboard-1.0.0.dist-info/METADATA
legend_dashboard-1.0.0.dist-info/WHEEL
legend_dashboard-1.0.0.dist-info/entry_points.txt
legend_dashboard-1.0.0.dist-info/top_level.txt
legend_dashboard-1.0.0.dist-info/RECORD
